LICENSE
MANIFEST.in
README.rst
requirements.txt
setup.py
async_notifications/__init__.py
async_notifications/admin.py
async_notifications/apps.py
async_notifications/forms.py
async_notifications/interfaces.py
async_notifications/lookups.py
async_notifications/mail_utils.py
async_notifications/models.py
async_notifications/newsletter_utils.py
async_notifications/register.py
async_notifications/settings.py
async_notifications/signals.py
async_notifications/tasks.py
async_notifications/tests.py
async_notifications/urls.py
async_notifications/utils.py
async_notifications/views.py
async_notifications/widgets.py
async_notifications.egg-info/PKG-INFO
async_notifications.egg-info/SOURCES.txt
async_notifications.egg-info/dependency_links.txt
async_notifications.egg-info/not-zip-safe
async_notifications.egg-info/requires.txt
async_notifications.egg-info/top_level.txt
async_notifications/locale/es/LC_MESSAGES/django.mo
async_notifications/locale/es/LC_MESSAGES/django.po
async_notifications/markitup/__init__.py
async_notifications/markitup/views.py
async_notifications/migrations/0001_initial.py
async_notifications/migrations/0002_auto_20160515_0018.py
async_notifications/migrations/0003_templatecontext.py
async_notifications/migrations/0004_auto_20200228_1653.py
async_notifications/migrations/0005_auto_20200517_1932.py
async_notifications/migrations/0006_newslettertask_task_id.py
async_notifications/migrations/0007_newsletter_filters.py
async_notifications/migrations/0008_remove_newslettertemplate_file_path.py
async_notifications/migrations/__init__.py
async_notifications/static/async_notifications/newsletter_formchange.css
async_notifications/static/async_notifications/previewupdater.js
async_notifications/static/async_notifications/tagify.js
async_notifications/templates/admin/async_notifications/newsletter/change_form.html
async_notifications/templates/async_notifications/base.html
async_notifications/templates/async_notifications/recipients.html
async_notifications/templates/widgets/tagifyselect.html